LICENSE
README.md
pyproject.toml
src/fig2sketch.py
src/converter/__init__.py
src/converter/base.py
src/converter/component.py
src/converter/config.py
src/converter/context.py
src/converter/convert.py
src/converter/document.py
src/converter/errors.py
src/converter/font.py
src/converter/font_features.py
src/converter/frame.py
src/converter/group.py
src/converter/instance.py
src/converter/layout.py
src/converter/meta.py
src/converter/page.py
src/converter/positioning.py
src/converter/prototype.py
src/converter/rectangle.py
src/converter/shape.py
src/converter/shape_group.py
src/converter/shape_path.py
src/converter/slice.py
src/converter/style.py
src/converter/symbol.py
src/converter/text.py
src/converter/tree.py
src/converter/user.py
src/converter/utils.py
src/fig2sketch.egg-info/PKG-INFO
src/fig2sketch.egg-info/SOURCES.txt
src/fig2sketch.egg-info/dependency_links.txt
src/fig2sketch.egg-info/entry_points.txt
src/fig2sketch.egg-info/requires.txt
src/fig2sketch.egg-info/top_level.txt
src/figformat/__init__.py
src/figformat/decodefig.py
src/figformat/fig2tree.py
src/figformat/kiwi.py
src/figformat/vector_network.py
src/sketchformat/__init__.py
src/sketchformat/common.py
src/sketchformat/document.py
src/sketchformat/layer_common.py
src/sketchformat/layer_group.py
src/sketchformat/layer_shape.py
src/sketchformat/prototype.py
src/sketchformat/style.py
src/sketchformat/text.py
src/sketchformat/serialize/__init__.py
src/sketchformat/serialize/json.py
src/sketchformat/serialize/orjson.py