Metadata-Version: 2.4
Name: fig2sketch
Version: 0.4.4
Requires-Python: >=3.10
License-File: LICENSE
Requires-Dist: Pillow==11.1.0
Requires-Dist: fonttools==4.43.0
Requires-Dist: appdirs==1.4.4
Requires-Dist: zstd==1.5.5.1
Provides-Extra: fast
Requires-Dist: fig-kiwi==0.1.2; extra == "fast"
Provides-Extra: dev
Requires-Dist: black==24.2.0; extra == "dev"
Requires-Dist: mypy==0.991; extra == "dev"
Requires-Dist: pytest==8.2.0; extra == "dev"
Requires-Dist: fig-kiwi==0.1.2; extra == "dev"
Dynamic: license-file
